{
	"configurations" : 
	[
		{
			"directories" : 
			[
				{
					"build" : ".",
					"childIndexes" : 
					[
						1
					],
					"hasInstallRule" : true,
					"minimumCMakeVersion" : 
					{
						"string" : "3.20"
					},
					"projectIndex" : 0,
					"source" : ".",
					"targetIndexes" : 
					[
						0
					]
				},
				{
					"build" : "build",
					"hasInstallRule" : true,
					"minimumCMakeVersion" : 
					{
						"string" : "3.16"
					},
					"parentIndex" : 0,
					"projectIndex" : 1,
					"source" : "/home/mhengelmolen/val3dity",
					"targetIndexes" : 
					[
						1,
						2
					]
				}
			],
			"name" : "Release",
			"projects" : 
			[
				{
					"childIndexes" : 
					[
						1
					],
					"directoryIndexes" : 
					[
						0
					],
					"name" : "backend",
					"targetIndexes" : 
					[
						0
					]
				},
				{
					"directoryIndexes" : 
					[
						1
					],
					"name" : "val3dity",
					"parentIndex" : 0,
					"targetIndexes" : 
					[
						1,
						2
					]
				}
			],
			"targets" : 
			[
				{
					"directoryIndex" : 0,
					"id" : "backend::@6890427a1f51a3e7e1df",
					"jsonFile" : "target-backend-Release-f29aba5ea1376c40e36e.json",
					"name" : "backend",
					"projectIndex" : 0
				},
				{
					"directoryIndex" : 1,
					"id" : "thirdparty::@039278ea0a093c55e3e1",
					"jsonFile" : "target-thirdparty-Release-dede2b0dc90cc481dfa0.json",
					"name" : "thirdparty",
					"projectIndex" : 1
				},
				{
					"directoryIndex" : 1,
					"id" : "val3dity::@039278ea0a093c55e3e1",
					"jsonFile" : "target-val3dity-Release-2e291766e24f71cb1ad1.json",
					"name" : "val3dity",
					"projectIndex" : 1
				}
			]
		}
	],
	"kind" : "codemodel",
	"paths" : 
	{
		"build" : "/home/mhengelmolen/Prototype/website/backend/cmake-build-release",
		"source" : "/home/mhengelmolen/Prototype/website/backend"
	},
	"version" : 
	{
		"major" : 2,
		"minor" : 2
	}
}
